aiohttp_client.py
aiohttp_client_manager-1.1.2.dist-info/LICENSE
aiohttp_client_manager-1.1.2.dist-info/METADATA
aiohttp_client_manager-1.1.2.dist-info/WHEEL
aiohttp_client_manager-1.1.2.dist-info/top_level.txt
aiohttp_client_manager-1.1.2.dist-info/zip-safe
aiohttp_client_manager-1.1.2.dist-info/RECORD
