Metadata-Version: 2.1
Name: aiohttp-client-manager
Version: 1.1.2
Summary: Automatic aiohttp ClientSession management
Home-page: https://pypi.python.org/pypi/aiohttp_client_manager
Author: Nathan Van Gheem
Author-email: vangheem@gmail.com
License: BSD
Keywords: aiohttp client session management
Platform: UNKNOWN
Classifier: Programming Language :: Python :: 3.6
Classifier: Topic :: Software Development :: Libraries :: Python Modules
Provides-Extra: test
